scrapy_aiohttp_downloader/__init__.py
scrapy_aiohttp_downloader/handler.py
scrapy_aiohttp_downloader/parser.py
scrapy_aiohttp_downloader-1.0.0b2.dist-info/LICENSE
scrapy_aiohttp_downloader-1.0.0b2.dist-info/METADATA
scrapy_aiohttp_downloader-1.0.0b2.dist-info/WHEEL
scrapy_aiohttp_downloader-1.0.0b2.dist-info/top_level.txt
scrapy_aiohttp_downloader-1.0.0b2.dist-info/RECORD
