Metadata-Version: 2.1
Name: scrapy-aiohttp-downloader
Version: 1.0.0b2
Summary: Scrapy download handler that integrates aiohttp
Home-page: https://github.com/jxlil/scrapy-aiohttp-downloader
Author: Jalil SA (jxlil)
License: MIT
Classifier: Programming Language :: Python :: 3
Classifier: Programming Language :: Python :: 3.12
Classifier: License :: OSI Approved :: MIT License
Requires-Python: >=3.12
License-File: LICENSE
Requires-Dist: aiohttp>=3.9.3
Requires-Dist: scrapy>=2.11.1
